mobsfscan/__init__.py
mobsfscan/__main__.py
mobsfscan/exceptions.py
mobsfscan/logger.py
mobsfscan/manifest.py
mobsfscan/manifest_metadata.py
mobsfscan/mobsfscan.py
mobsfscan/settings.py
mobsfscan/utils.py
mobsfscan/formatters/__init__.py
mobsfscan/formatters/cli.py
mobsfscan/formatters/json_fmt.py
mobsfscan/formatters/sarif.py
mobsfscan/formatters/sonarqube.py
mobsfscan/rules/patterns/android/kotlin/best_practices.yaml
mobsfscan/rules/patterns/android/kotlin/kotlin_rules.yaml
mobsfscan/rules/patterns/ios/objectivec/best_practices.yaml
mobsfscan/rules/patterns/ios/objectivec/objective_c_rules.yaml
mobsfscan/rules/patterns/ios/swift/best_practices.yaml
mobsfscan/rules/patterns/ios/swift/swift_rules.yaml
mobsfscan/rules/semgrep/android/hidden_ui.yaml
mobsfscan/rules/semgrep/android/logging.yaml
mobsfscan/rules/semgrep/android/secrets.yaml
mobsfscan/rules/semgrep/android/word_readable_writable.yaml
mobsfscan/rules/semgrep/best_practices/android_safetynetapi.yaml
mobsfscan/rules/semgrep/best_practices/flag_secure.yaml
mobsfscan/rules/semgrep/best_practices/root_detection.yaml
mobsfscan/rules/semgrep/best_practices/tapjacking.yaml
mobsfscan/rules/semgrep/best_practices/tls_certificate_transparency.yaml
mobsfscan/rules/semgrep/best_practices/tls_pinning.yaml
mobsfscan/rules/semgrep/crypto/aes_ecb.yaml
mobsfscan/rules/semgrep/crypto/aes_encryption_keys.yaml
mobsfscan/rules/semgrep/crypto/cbc_padding_oracle.yaml
mobsfscan/rules/semgrep/crypto/cbc_static_iv.yaml
mobsfscan/rules/semgrep/crypto/insecure_random.yaml
mobsfscan/rules/semgrep/crypto/insecure_ssl_v3.yaml
mobsfscan/rules/semgrep/crypto/rsa_no_oeap.yaml
mobsfscan/rules/semgrep/crypto/sha1_hash.yaml
mobsfscan/rules/semgrep/crypto/weak_ciphers.yaml
mobsfscan/rules/semgrep/crypto/weak_hashes.yaml
mobsfscan/rules/semgrep/crypto/weak_iv.yaml
mobsfscan/rules/semgrep/crypto/weak_key_size.yaml
mobsfscan/rules/semgrep/deserialization/jackson_deserialization.yaml
mobsfscan-0.4.5.dist-info/LICENSE
mobsfscan-0.4.5.dist-info/METADATA
mobsfscan-0.4.5.dist-info/WHEEL
mobsfscan-0.4.5.dist-info/entry_points.txt
mobsfscan-0.4.5.dist-info/top_level.txt
mobsfscan-0.4.5.dist-info/RECORD
