Metadata-Version: 2.1
Name: mobsfscan
Version: 0.4.5
Summary: mobsfscan is a static analysis tool that can find insecure code patterns in your Android and iOS source code. Supports Java, Kotlin, Swift, and Objective C Code.
Home-page: https://github.com/MobSF/mobsfscan
Author: Ajin Abraham
Author-email: ajin25@gmail.com
Classifier: Development Status :: 4 - Beta
Classifier: Intended Audience :: Developers
Classifier: License :: OSI Approved :: GNU Lesser General Public License v3 or later (LGPLv3+)
Classifier: Programming Language :: Python :: 3.7
License-File: LICENSE
Requires-Dist: colorama>=0.4.5
Requires-Dist: libsast>=3.1.5
Requires-Dist: semgrep==1.86.0
Requires-Dist: sarif-om>=1.0.4
Requires-Dist: jschema-to-python>=1.2.3
Requires-Dist: tabulate>=0.8.10
Requires-Dist: xmltodict>=0.13.0
